{
  "apps": [
    {
      "name": "MLib",
      "id": "MLib",
      "url": "https://cattn.github.io/MLib/",
      "icon": "assets/spotify.png",
      "width": "1200px",
      "height": "600px",
      "startup": "false"
    },
    {
      "name": "gba",
      "id": "gba",
      "url": "https://cattn.github.io/GBA2.0/",
      "icon": "assets/GBA_2_Icon_ver3.png",
      "width": "1200px",
      "height": "600px",
      "startup": "true"
    },
    {
      "name": "Bing",
      "id": "Bing",
      "url": "https://bing.com",
      "icon": "assets/chrome.ico",
      "width": "800px",
      "height": "600px",
      "startup": "false"
    },
    {
      "name": "Discord",
      "id": "Discord",
      "url": "https://discord.com/app",
      "icon": "assets/discord.ico",
      "width": "800px",
      "height": "600px",
      "startup": "false"
    },
    {
      "name": "Settings App",
      "id": "settings",
      "url": "settings/index.html",
      "icon": "assets/settings.ico",
      "width": "1000px",
      "height": "600px",
      "startup": "true"
    },
    {
      "name": "Bing2",
      "id": "Bing2",
      "url": "https://bing.com",
      "icon": "assets/chrome.ico",
      "width": "800px",
      "height": "600px",
      "startup": "false"
    }
  ]
}
